anipick/__init__.py
anipick/animpedia.py
anipick/char.py
anipick/error_handling.py
anipick/genshin.py
anipick/isi.py
anipick/lyricsnim.py
anipick/manga.py
anipick/pict.py
anipick/quotepedia.py
anipick/season.py
anipick/secret.py
Anipick-1.7.0.dist-info/LICENSE.txt
Anipick-1.7.0.dist-info/METADATA
Anipick-1.7.0.dist-info/WHEEL
Anipick-1.7.0.dist-info/entry_points.txt
Anipick-1.7.0.dist-info/top_level.txt
Anipick-1.7.0.dist-info/RECORD
