Metadata-Version: 2.1
Name: Anipick
Version: 1.7.0
Summary: Anime module for search Anime, Manga, Quote info
Home-page: https://github.com/pengode-handal/anipick
Author: Kenzawa/Babwa
Author-email: babwaxgura@gmail.com
License: MIT
Keywords: anipick,Anipick,anime,python3,python,Anime,images
Platform: UNKNOWN
Classifier: Development Status :: 5 - Production/Stable
Classifier: Intended Audience :: Developers
Classifier: Operating System :: OS Independent
Classifier: License :: OSI Approved :: MIT License
Classifier: Programming Language :: Python :: 3
Classifier: Topic :: Software Development :: Libraries
Requires-Python: >=3.6
License-File: LICENSE.txt
Requires-Dist: requests (>=2.18.4)
Requires-Dist: bs4 (>=0.0.1)
Requires-Dist: googlesearch-python (>=1.0.1)
Requires-Dist: tabulate (>=0.8.7)
Requires-Dist: rich (>=10.9.0)
